Workbook

Sheet Orad (internal)
A1: IMPORTANT – THIS IS NOT A REAL, FORMAL OR OFFICIAL PROPOSAL. It is an example only, prepared to support the offer that Orad must make to the end client.
A2: Price list for the client – Example Proposal 2
A3: Example Proposal 2 · Yoseftal Medical Center, Eilat · ORAD-YOS-EX2-2026-10 · 26/10/2026
A4: 2 ward sections · 13 rooms × 3 beds (8 + 5) · 13 en-suite bathrooms · 2 nurse stations · 1 shared server
C6: Orad margin (all items) | G6: 0.35
C7: Exchange rate ILS / EUR | G7: 3.9
A9: Photo | B9: Code | C9: Description | D9: Unit | E9: Qty in project | F9: ACE BG net (cost) | G9: Orad margin | H9: Client price EUR | I9: Client price ILS | J9: Project value EUR (client)
B10: ACE82012153 | C10: Bed call panel, red, with bayonet socket for pear handset | D10: pcs | E10: 39 | F10: 67.13 | G10: =$G$6 -> 0.35 | H10: =ROUND(F10*(1+G10),2) -> 90.63 | I10: =ROUND(H10*$G$7,2) -> 353.46 | J10: =E10*H10 -> 3534.57
B11: ACE39060521 | C11: Pear handset, 1 capacitive button, 2 m cable, bayonet | D11: pcs | E11: 39 | F11: 56.05 | G11: =$G$6 -> 0.35 | H11: =ROUND(F11*(1+G11),2) -> 75.67 | I11: =ROUND(H11*$G$7,2) -> 295.11 | J11: =E11*H11 -> 2951.13
B12: ACE82082137 | C12: Presence / cancel panel, green | D12: pcs | E12: 26 | F12: 67.13 | G12: =$G$6 -> 0.35 | H12: =ROUND(F12*(1+G12),2) -> 90.63 | I12: =ROUND(H12*$G$7,2) -> 353.46 | J12: =E12*H12 -> 2356.38
B13: ACE40320303 | C13: SOS mechanism with pull-cord (toilet / shower) | D13: pcs | E13: 26 | F13: 44.1 | G13: =$G$6 -> 0.35 | H13: =ROUND(F13*(1+G13),2) -> 59.54 | I13: =ROUND(H13*$G$7,2) -> 232.21 | J13: =E13*H13 -> 1548.04
B14: EOP004 | C14: Corridor light, 3 colours (red · green · blue) | D14: pcs | E14: 26 | F14: 128.57 | G14: =$G$6 -> 0.35 | H14: =ROUND(F14*(1+G14),2) -> 173.57 | I14: =ROUND(H14*$G$7,2) -> 676.92 | J14: =E14*H14 -> 4512.82
B15: ECV169 | C15: Room controller PCB 24 pins, 12–48 V DC | D15: pcs | E15: 39 | F15: 114.29 | G15: =$G$6 -> 0.35 | H15: =ROUND(F15*(1+G15),2) -> 154.29 | I15: =ROUND(H15*$G$7,2) -> 601.73 | J15: =E15*H15 -> 6017.31
B16: EVV049 | C16: SmartHub connectia – head of the controller bus | D16: pcs | E16: 2 | F16: 928.57 | G16: =$G$6 -> 0.35 | H16: =ROUND(F16*(1+G16),2) -> 1253.57 | I16: =ROUND(H16*$G$7,2) -> 4888.92 | J16: =E16*H16 -> 2507.14
B17: EOP006 | C17: LVNS server – local server & notifications | D17: pcs | E17: 1 | F17: 1857.14 | G17: =$G$6 -> 0.35 | H17: =ROUND(F17*(1+G17),2) -> 2507.14 | I17: =ROUND(H17*$G$7,2) -> 9777.85 | J17: =E17*H17 -> 2507.14
B18: EOP002 | C18: Nurse station iPad 10.9" Wi-Fi 128 GB | D18: pcs | E18: 2 | F18: 655.56 | G18: =$G$6 -> 0.35 | H18: =ROUND(F18*(1+G18),2) -> 885.01 | I18: =ROUND(H18*$G$7,2) -> 3451.54 | J18: =E18*H18 -> 1770.02
B19: EVV038 | C19: ionTab client/server licences + MDM (1st year included) | D19: pcs | E19: 2 | F19: 284.29 | G19: =$G$6 -> 0.35 | H19: =ROUND(F19*(1+G19),2) -> 383.79 | I19: =ROUND(H19*$G$7,2) -> 1496.78 | J19: =E19*H19 -> 767.58
B20: ACESWP24P | C20: PoE switch 24 ports, managed | D20: pcs | E20: 2 | F20: 287.46 | G20: =$G$6 -> 0.35 | H20: =ROUND(F20*(1+G20),2) -> 388.07 | I20: =ROUND(H20*$G$7,2) -> 1513.47 | J20: =E20*H20 -> 776.14
B21: RACK9U | C21: Wall rack 19" 9U with PDU, shelf and cable management | D21: pcs | E21: 2 | F21: 320 | G21: =$G$6 -> 0.35 | H21: =ROUND(F21*(1+G21),2) -> 432 | I21: =ROUND(H21*$G$7,2) -> 1684.8 | J21: =E21*H21 -> 864
... B23: WAP6 | C23: Wi-Fi 6 access point, PoE, at the nurse station | D23: pcs | E23: 2 | F23: 220 | G23: =$G$6 -> 0.35 | H23: =ROUND(F23*(1+G23),2) -> 297 | I23: =ROUND(H23*$G$7,2) -> 1158.3 | J23: =E23*H23 -> 594
C24: Project value at client prices | J24: =SUM(J10:J23) -> 32002.27
C26: • Prices in EUR and ILS, VAT not included. Exchange rate used: (G7) ILS/EUR (example – update in the Excel).
C27: • Installation, cabling and commissioning are quoted separately.
C28: Yellow = editable input (discount, estimate or price to confirm). Blue = input, black = formula. Change the yellow discount cell to apply a new discount to everything, or change a category / line discount.
A30: EXAMPLE ONLY – NOT A REAL, FORMAL OR OFFICIAL PROPOSAL

Sheet Client price list
A1: IMPORTANT – THIS IS NOT A REAL, FORMAL OR OFFICIAL PROPOSAL. It is an example only, prepared to support the offer that Orad must make to the end client.
A2: Price list for the client
A3: Example Proposal 2 · Yoseftal Medical Center, Eilat · ORAD-YOS-EX2-2026-10 · 26/10/2026
A4: 2 ward sections · 13 rooms × 3 beds (8 + 5) · 13 en-suite bathrooms · 2 nurse stations · 1 shared server
A9: Photo | B9: Code | C9: Description | D9: Unit | E9: Price EUR | F9: Price ILS
B10: ='Orad (internal)'!B10 -> ACE82012153 | C10: ='Orad (internal)'!C10 -> Bed call panel, red, with bayonet socket for pear handset | D10: ='Orad (internal)'!D10 -> pcs | E10: ='Orad (internal)'!H10 -> 90.63 | F10: ='Orad (internal)'!I10 -> 353.46
B11: ='Orad (internal)'!B11 -> ACE39060521 | C11: ='Orad (internal)'!C11 -> Pear handset, 1 capacitive button, 2 m cable, bayonet | D11: ='Orad (internal)'!D11 -> pcs | E11: ='Orad (internal)'!H11 -> 75.67 | F11: ='Orad (internal)'!I11 -> 295.11
B12: ='Orad (internal)'!B12 -> ACE82082137 | C12: ='Orad (internal)'!C12 -> Presence / cancel panel, green | D12: ='Orad (internal)'!D12 -> pcs | E12: ='Orad (internal)'!H12 -> 90.63 | F12: ='Orad (internal)'!I12 -> 353.46
B13: ='Orad (internal)'!B13 -> ACE40320303 | C13: ='Orad (internal)'!C13 -> SOS mechanism with pull-cord (toilet / shower) | D13: ='Orad (internal)'!D13 -> pcs | E13: ='Orad (internal)'!H13 -> 59.54 | F13: ='Orad (internal)'!I13 -> 232.21
B14: ='Orad (internal)'!B14 -> EOP004 | C14: ='Orad (internal)'!C14 -> Corridor light, 3 colours (red · green · blue) | D14: ='Orad (internal)'!D14 -> pcs | E14: ='Orad (internal)'!H14 -> 173.57 | F14: ='Orad (internal)'!I14 -> 676.92
B15: ='Orad (internal)'!B15 -> ECV169 | C15: ='Orad (internal)'!C15 -> Room controller PCB 24 pins, 12–48 V DC | D15: ='Orad (internal)'!D15 -> pcs | E15: ='Orad (internal)'!H15 -> 154.29 | F15: ='Orad (internal)'!I15 -> 601.73
B16: ='Orad (internal)'!B16 -> EVV049 | C16: ='Orad (internal)'!C16 -> SmartHub connectia – head of the controller bus | D16: ='Orad (internal)'!D16 -> pcs | E16: ='Orad (internal)'!H16 -> 1253.57 | F16: ='Orad (internal)'!I16 -> 4888.92
B17: ='Orad (internal)'!B17 -> EOP006 | C17: ='Orad (internal)'!C17 -> LVNS server – local server & notifications | D17: ='Orad (internal)'!D17 -> pcs | E17: ='Orad (internal)'!H17 -> 2507.14 | F17: ='Orad (internal)'!I17 -> 9777.85
B18: ='Orad (internal)'!B18 -> EOP002 | C18: ='Orad (internal)'!C18 -> Nurse station iPad 10.9" Wi-Fi 128 GB | D18: ='Orad (internal)'!D18 -> pcs | E18: ='Orad (internal)'!H18 -> 885.01 | F18: ='Orad (internal)'!I18 -> 3451.54
B19: ='Orad (internal)'!B19 -> EVV038 | C19: ='Orad (internal)'!C19 -> ionTab client/server licences + MDM (1st year included) | D19: ='Orad (internal)'!D19 -> pcs | E19: ='Orad (internal)'!H19 -> 383.79 | F19: ='Orad (internal)'!I19 -> 1496.78
B20: ='Orad (internal)'!B20 -> ACESWP24P | C20: ='Orad (internal)'!C20 -> PoE switch 24 ports, managed | D20: ='Orad (internal)'!D20 -> pcs | E20: ='Orad (internal)'!H20 -> 388.07 | F20: ='Orad (internal)'!I20 -> 1513.47
B21: ='Orad (internal)'!B21 -> RACK9U | C21: ='Orad (internal)'!C21 -> Wall rack 19" 9U with PDU, shelf and cable management | D21: ='Orad (internal)'!D21 -> pcs | E21: ='Orad (internal)'!H21 -> 432 | F21: ='Orad (internal)'!I21 -> 1684.8
... B23: ='Orad (internal)'!B23 -> WAP6 | C23: ='Orad (internal)'!C23 -> Wi-Fi 6 access point, PoE, at the nurse station | D23: ='Orad (internal)'!D23 -> pcs | E23: ='Orad (internal)'!H23 -> 297 | F23: ='Orad (internal)'!I23 -> 1158.3
C25: • Prices in EUR and ILS, VAT not included. Exchange rate used: 'Orad (internal)'!G7 ILS/EUR (example – update in the Excel).
C26: • Installation, cabling and commissioning are quoted separately.
A28: EXAMPLE ONLY – NOT A REAL, FORMAL OR OFFICIAL PROPOSAL
